CHANGES.txt
LICENSE.txt
MANIFEST.in
README.txt
setup.py
Geo2D.egg-info/PKG-INFO
Geo2D.egg-info/SOURCES.txt
Geo2D.egg-info/dependency_links.txt
Geo2D.egg-info/top_level.txt
docs/html/_sources/index.txt
docs/html/_sources/_templates/autosummary/class.txt
docs/html/_sources/api/bib.txt
docs/html/_sources/api/geo2d.txt
docs/html/_sources/api/modules.txt
docs/html/_sources/api/geometry/geo2d.geometry.BoundingBox.txt
docs/html/_sources/api/geometry/geo2d.geometry.GeometricObject.txt
docs/html/_sources/api/geometry/geo2d.geometry.Line.txt
docs/html/_sources/api/geometry/geo2d.geometry.Point.txt
docs/html/_sources/api/geometry/geo2d.geometry.Polygon.txt
docs/html/_sources/api/geometry/geo2d.geometry.Ray.txt
docs/html/_sources/api/geometry/geo2d.geometry.Segment.txt
docs/html/_sources/api/geometry/geo2d.geometry.Vector.txt
docs/html/_sources/api/geometry/geo2d.geometry.get_perpendicular_to.txt
docs/html/_sources/api/utils/geo2d.utils.cached_property.txt
docs/html/_sources/api/utils/geo2d.utils.find_first_missing.txt
docs/html/_sources/api/utils/geo2d.utils.float_to_2pi.txt
docs/html/_sources/api/utils/geo2d.utils.rotated.txt
geo2d/__init__.py
geo2d/geometry.py
geo2d/utils.py
geo2d/test/__init__.py
geo2d/test/test_geometry.py
geo2d/test/test_utils.py