Metadata-Version: 1.0
Name: Geo2D
Version: 0.1.21
Summary: Pure Python (3 compatible) geometry package.
Home-page: http://launchpad.net/geo2d
Author: Razvan C. Radulescu
Author-email: razvanc87@gmail.com
License: LICENSE.txt
Platform: UNKNOWN
